segmentation_refinement/__init__.py
segmentation_refinement/download.py
segmentation_refinement/eval_helper.py
segmentation_refinement/main.py
segmentation_refinement/models/__init__.py
segmentation_refinement/models/psp/__init__.py
segmentation_refinement/models/psp/extractors.py
segmentation_refinement/models/psp/pspnet.py
segmentation_refinement-0.6.dist-info/LICENSE
segmentation_refinement-0.6.dist-info/METADATA
segmentation_refinement-0.6.dist-info/WHEEL
segmentation_refinement-0.6.dist-info/top_level.txt
segmentation_refinement-0.6.dist-info/RECORD
