Metadata-Version: 2.1
Name: segmentation-refinement
Version: 0.6
Summary: Deep learning based segmentation refinement system.
Home-page: https://github.com/hkchengrex/CascadePSP
Author: Ho Kei Cheng, Jihoon Chung
Author-email: hkchengrex@gmail.com
Classifier: Programming Language :: Python :: 3
Classifier: License :: OSI Approved :: MIT License
Classifier: Operating System :: OS Independent
Requires-Python: >=3.6
License-File: LICENSE
Requires-Dist: torch
Requires-Dist: torchvision
Requires-Dist: requests
